setup.cfg
setup.py
ooo2tools.core.egg-info/PKG-INFO
ooo2tools.core.egg-info/SOURCES.txt
ooo2tools.core.egg-info/dependency_links.txt
ooo2tools.core.egg-info/entry_points.txt
ooo2tools.core.egg-info/not-zip-safe
ooo2tools.core.egg-info/top_level.txt
ooo2toolscore/__init__.py
ooo2toolscore/able_toconnect.py
ooo2toolscore/all.py
ooo2toolscore/convert2pdf.py
ooo2toolscore/footer.py
ooo2toolscore/raa.py
ooo2toolscore/raaacte.py
ooo2toolscore/raarecueil.py
ooo2toolscore/standard.py