Metadata-Version: 1.0
Name: ooo2tools.core
Version: 0.1dev
Summary: manage your documents with a built-in macro system via a server instance of OOo2
Home-page: http://plone.org/products/ooo2tools
Author: Jean-Michel FRANCOIS
Author-email: UNKNOWN
License: GPL
Keywords: open office pyuno
Platform: UNKNOWN
